{
      "Channel_Name": "IsraelEurope",
      "Channel_ID": -1001669001944,
      "Channel_Description": "A project by @ArmyFreaks @DisasterFreaks @RoadToPetabyte @DefenceTelegram @WarningAlertTelegram — More news @IsraelDefenseForcesTelegram @IronDomeTelegram @IsraeliWarNews @IsraelTelegramChannels @natovideos @natoarmynews etc.",
      "Channel_Members": {
            "Count": 308,
            "Last_updated": "10.05.2024"
      },
      "Factcheck_Count": {
            "Count": 1,
            "Last_updated": "31.12.2023"
      }
}